odoo/addons/test_ssi_sequence_mixin/README.rst
odoo/addons/test_ssi_sequence_mixin/__init__.py
odoo/addons/test_ssi_sequence_mixin/__manifest__.py
odoo/addons/test_ssi_sequence_mixin/models/__init__.py
odoo/addons/test_ssi_sequence_mixin/models/test_sequence.py
odoo/addons/test_ssi_sequence_mixin/security/ir.model.access.csv
odoo/addons/test_ssi_sequence_mixin/static/description/icon.png
odoo/addons/test_ssi_sequence_mixin/views/test_sequence_view.xml
odoo14_addon_test_ssi_sequence_mixin-14.0.1.1.0.dist-info/METADATA
odoo14_addon_test_ssi_sequence_mixin-14.0.1.1.0.dist-info/WHEEL
odoo14_addon_test_ssi_sequence_mixin-14.0.1.1.0.dist-info/top_level.txt
odoo14_addon_test_ssi_sequence_mixin-14.0.1.1.0.dist-info/RECORD
